pykeepass/__init__.py
pykeepass/attachment.py
pykeepass/baseelement.py
pykeepass/blank_database.kdbx
pykeepass/deprecated.py
pykeepass/entry.py
pykeepass/exceptions.py
pykeepass/group.py
pykeepass/icons.py
pykeepass/pykeepass.py
pykeepass/setters.py
pykeepass/version.py
pykeepass/xpath.py
pykeepass/kdbx_parsing/__init__.py
pykeepass/kdbx_parsing/common.py
pykeepass/kdbx_parsing/kdbx.py
pykeepass/kdbx_parsing/kdbx3.py
pykeepass/kdbx_parsing/kdbx4.py
pykeepass/kdbx_parsing/pytwofish.py
pykeepass/kdbx_parsing/twofish.py
pykeepass-4.1.1.dist-info/LICENSE
pykeepass-4.1.1.dist-info/METADATA
pykeepass-4.1.1.dist-info/WHEEL
pykeepass-4.1.1.dist-info/top_level.txt
pykeepass-4.1.1.dist-info/RECORD
