Metadata-Version: 2.2
Name: pykeepass
Version: 4.1.1
Summary: Python library to interact with keepass databases (supports KDBX3 and KDBX4)
Author-email: Philipp Schmitt <philipp@schmitt.co>, Evan Widloski <evan_gh@widloski.com>
License: GPL-3.0
Project-URL: Homepage, https://github.com/libkeepass/pykeepass
Project-URL: Repository, https://github.com/libkeepass/pykeepass
Project-URL: Issues, https://github.com/libkeepass/pykeepass/issues
Project-URL: Changelog, https://github.com/libkeepass/pykeepass/blob/master/CHANGELOG.rst
Keywords: vault,keepass
Classifier: Topic :: Security
Classifier: Topic :: Software Development :: Libraries
Classifier: License :: OSI Approved :: GNU General Public License v3 (GPLv3)
Classifier: Programming Language :: Python :: 3.7
Classifier: Programming Language :: Python :: 3.8
Classifier: Programming Language :: Python :: 3.9
Classifier: Programming Language :: Python :: 3.10
Classifier: Programming Language :: Python :: 3.11
Requires-Python: >=3.7
License-File: LICENSE
Requires-Dist: pyotp>=2.9.0
Requires-Dist: setuptools; python_version < "3.8"
Requires-Dist: construct>=2.10.53
Requires-Dist: argon2_cffi>=18.1.0
Requires-Dist: pycryptodomex>=3.6.2
Requires-Dist: lxml
Provides-Extra: test
Requires-Dist: pyotp; extra == "test"
Requires-Dist: pdoc; extra == "test"
